MANIFEST.in
README.rst
buildout.cfg
requirements.txt
setup.py
version.txt
bob/__init__.py
bob.bio.face_ongoing.egg-info/PKG-INFO
bob.bio.face_ongoing.egg-info/SOURCES.txt
bob.bio.face_ongoing.egg-info/dependency_links.txt
bob.bio.face_ongoing.egg-info/entry_points.txt
bob.bio.face_ongoing.egg-info/not-zip-safe
bob.bio.face_ongoing.egg-info/requires.txt
bob.bio.face_ongoing.egg-info/top_level.txt
bob/bio/__init__.py
bob/bio/face_ongoing/__init__.py
bob/bio/face_ongoing/baselines/__init__.py
bob/bio/face_ongoing/baselines/casianet.py
bob/bio/face_ongoing/baselines/cnn8.py
bob/bio/face_ongoing/baselines/databases.py
bob/bio/face_ongoing/baselines/drgan.py
bob/bio/face_ongoing/baselines/experimental.py
bob/bio/face_ongoing/baselines/facenet.py
bob/bio/face_ongoing/baselines/idiap_inception_v1.py
bob/bio/face_ongoing/baselines/idiap_inception_v2.py
bob/bio/face_ongoing/baselines/rankone.py
bob/bio/face_ongoing/baselines/vgg16tf.py
bob/bio/face_ongoing/configs/__init__.py
bob/bio/face_ongoing/configs/baselines/casianet/default_crop.py
bob/bio/face_ongoing/configs/baselines/casianet/extractor.py
bob/bio/face_ongoing/configs/baselines/casianet/eyes_crop.py
bob/bio/face_ongoing/configs/baselines/casiawebface/experimental.py
bob/bio/face_ongoing/configs/baselines/casiawebface/inception_resnet_v1/centerloss_gray.py
bob/bio/face_ongoing/configs/baselines/casiawebface/inception_resnet_v1/centerloss_rgb.py
bob/bio/face_ongoing/configs/baselines/casiawebface/inception_resnet_v2/centerloss_gray.py
bob/bio/face_ongoing/configs/baselines/casiawebface/inception_resnet_v2/centerloss_rgb.py
bob/bio/face_ongoing/configs/baselines/cnn8/default_crop.py
bob/bio/face_ongoing/configs/baselines/cnn8/extractor.py
bob/bio/face_ongoing/configs/baselines/cnn8/eyes_crop.py
bob/bio/face_ongoing/configs/baselines/drgan/default_crop.py
bob/bio/face_ongoing/configs/baselines/drgan/extractor.py
bob/bio/face_ongoing/configs/baselines/drgan/eyes_crop.py
bob/bio/face_ongoing/configs/baselines/facenet_sandberg/inception_v1.py
bob/bio/face_ongoing/configs/baselines/inception_resnet_preprocessors/casia_webface_crop.py
bob/bio/face_ongoing/configs/baselines/inception_resnet_preprocessors/default_gray_crop.py
bob/bio/face_ongoing/configs/baselines/inception_resnet_preprocessors/default_rgb_crop.py
