Metadata-Version: 1.1
Name: bob.bio.face-ongoing
Version: 1.0.7
Summary: Tools for running face recognition experiments
Home-page: https://gitlab.idiap.ch/bob/bob.bio.face_ongoing
Author: Tiago de Freitas Pereira
Author-email: tiago.pereira@idiap.ch
License: BSD
Keywords: bob,biometric recognition,evaluation
Platform: UNKNOWN
Classifier: Framework :: Bob
Classifier: Development Status :: 3 - Alpha
Classifier: Intended Audience :: Developers
Classifier: License :: OSI Approved :: BSD License
Classifier: Natural Language :: English
Classifier: Programming Language :: Python
Classifier: Topic :: Scientific/Engineering :: Artificial Intelligence
